Metadata-Version: 2.1
Name: persistQueue
Version: 0.1.5
Summary: A implementation of Class for Persist Queue
Home-page: http://re91877z@10.55.200.102:7990/scm/edge/lib-persist-queue.git
Author: logicalis
Author-email: eugenio@eugenio.io
License: MIT
Keywords: queue,persistence,iot,embedded
Platform: UNKNOWN
Classifier: Development Status :: 4 - Beta
Classifier: Operating System :: OS Independent
Classifier: Intended Audience :: Developers
Classifier: Programming Language :: Python
Classifier: Programming Language :: Python :: Implementation
Classifier: Programming Language :: Python :: 2.7
Classifier: Topic :: Software Development :: Libraries
